omnibin/__init__.py
omnibin/metrics.py
omnibin/utils.py
omnibin-0.1.7.dist-info/METADATA
omnibin-0.1.7.dist-info/WHEEL
omnibin-0.1.7.dist-info/licenses/LICENSE
omnibin-0.1.7.dist-info/RECORD
