Metadata-Version: 2.4
Name: omnibin
Version: 0.1.7
Summary: A package for generating comprehensive binary classification reports with visualizations and confidence intervals
Project-URL: Homepage, https://github.com/kitamura-felipe/omnibin
Project-URL: Repository, https://github.com/kitamura-felipe/omnibin.git
Author-email: Felipe Campos Kitamura <kitamura.felipe@gmail.com>
License-Expression: MIT
License-File: LICENSE
Classifier: License :: OSI Approved :: MIT License
Classifier: Operating System :: OS Independent
Classifier: Programming Language :: Python :: 3
Requires-Python: >=3.11
Requires-Dist: matplotlib>=3.4.0
Requires-Dist: numpy>=1.21.0
Requires-Dist: pandas>=1.3.0
Requires-Dist: scikit-learn>=1.0.0
Requires-Dist: scipy>=1.7.0
Requires-Dist: seaborn>=0.11.0
